shorten_url/__init__.py
shorten_url/shorten_url.py
shorten_url-1.0.0.dist-info/LICENSE.txt
shorten_url-1.0.0.dist-info/METADATA
shorten_url-1.0.0.dist-info/WHEEL
shorten_url-1.0.0.dist-info/top_level.txt
shorten_url-1.0.0.dist-info/RECORD
